{
"n_orig" : 2,
"n_dest" : 2,
"origin": [{
            "name": "blue",
            "items": [{
                "name": "glass",
                "n": 5
            }]
        },
        {
            "name": "pink",
            "items": [{
                "name": "coco",
                "n": 3
            }]
        }
    ],

"destiny": [
     {
        "name": "blue",
        "items": [
            {
                "name": "glass",
                "n": 3
            },
            {
                "name": "coco",
                "n": 1
            }
        ]
    },
    {
        "name": "blue",
        "items": [
            {
                "name": "glass",
                "n": 2
            },
            {
                "name": "coco",
                "n": 2
            }
        ]
    }
  ]
}